MANIFEST.in
README.rst
bootstrap.py
buildout.cfg
setup.py
xbob/__init__.py
xbob.paper.tpami2013.egg-info/PKG-INFO
xbob.paper.tpami2013.egg-info/SOURCES.txt
xbob.paper.tpami2013.egg-info/dependency_links.txt
xbob.paper.tpami2013.egg-info/entry_points.txt
xbob.paper.tpami2013.egg-info/namespace_packages.txt
xbob.paper.tpami2013.egg-info/not-zip-safe
xbob.paper.tpami2013.egg-info/requires.txt
xbob.paper.tpami2013.egg-info/top_level.txt
xbob/paper/__init__.py
xbob/paper/tpami2013/__init__.py
xbob/paper/tpami2013/config_lfw.py
xbob/paper/tpami2013/config_multipie.py
xbob/paper/tpami2013/features.py
xbob/paper/tpami2013/lfw_features.py
xbob/paper/tpami2013/linear.py
xbob/paper/tpami2013/plda.py
xbob/paper/tpami2013/utils.py
xbob/paper/tpami2013/scripts/__init__.py
xbob/paper/tpami2013/scripts/concatenate_scores.py
xbob/paper/tpami2013/scripts/distance_scores.py
xbob/paper/tpami2013/scripts/experiment_pcaplda_lfw.py
xbob/paper/tpami2013/scripts/experiment_plda_subworld.py
xbob/paper/tpami2013/scripts/lbph_extraction.py
xbob/paper/tpami2013/scripts/lbph_features.py
xbob/paper/tpami2013/scripts/lda_train.py
xbob/paper/tpami2013/scripts/lfw_features.py
xbob/paper/tpami2013/scripts/linear_project.py
xbob/paper/tpami2013/scripts/meanmodel_enroll.py
xbob/paper/tpami2013/scripts/pca_features.py
xbob/paper/tpami2013/scripts/pca_train.py
xbob/paper/tpami2013/scripts/plda_enroll.py
xbob/paper/tpami2013/scripts/plda_example_iris.py
xbob/paper/tpami2013/scripts/plda_scores.py
xbob/paper/tpami2013/scripts/plda_train.py
xbob/paper/tpami2013/scripts/plot_figure2.py
xbob/paper/tpami2013/scripts/plot_table2.py
xbob/paper/tpami2013/scripts/plot_table3.py
xbob/paper/tpami2013/scripts/toolchain_lbph.py
xbob/paper/tpami2013/scripts/toolchain_lda.py
xbob/paper/tpami2013/scripts/toolchain_pca.py
xbob/paper/tpami2013/scripts/toolchain_pcaplda.py
xbob/paper/tpami2013/scripts/toolchain_plda.py