Metadata-Version: 1.1
Name: xbob.paper.tpami2013
Version: 0.3.0a0
Summary: Example on how to use the scalable implementation of PLDA and how to reproduce experiments of the article
Home-page: http://pypi.python.org/pypi/xbob.paper.tpami2013
Author: Laurent El Shafey
Author-email: Laurent.El-Shafey@idiap.ch
License: GPLv3
Platform: UNKNOWN
Classifier: Development Status :: 4 - Beta
Classifier: Intended Audience :: Education
Classifier: License :: OSI Approved :: GNU General Public License v3 (GPLv3)
Classifier: Natural Language :: English
Classifier: Programming Language :: Python
Classifier: Programming Language :: Python :: 3
Classifier: Topic :: Scientific/Engineering :: Artificial Intelligence
